daredata_snowconn
