Metadata-Version: 2.1
Name: daredata-snowconn
Version: 1.0.3
Summary: Python utilities for connection to the Snowflake data warehouse
Home-page: https://github.com/DareData/snowconn
Author: DareData Engineering
Author-email: sam@daredata.engineering
License: UNKNOWN
Platform: UNKNOWN
License-File: LICENSE
